phs/__init__.py
phs/cli.py
phs/data/FDDB_V6_mga_masking.csv
phs/geometry/__init__.py
phs/geometry/derived.py
phs/geometry/finder.py
phs/geometry/ray_tracing.py
phs/geometry/support.py
phs/modelling/__init__.py
phs/modelling/constraints.py
phs/modelling/mga.py
phs/modelling/rpwi.py
phs/modelling/swi.py
phs/setup.py
phs/timeline/.DS_Store
phs/timeline/__init__.py
phs/timeline/apl.py
phs/timeline/coverage.py
phs/timeline/event_parser.py
phs/timeline/event_resolver.py
phs/timeline/itl.py
phs/timeline/opl.py
phs/timeline/ptr.py
phs/timeline/schema_validator.py
phs/timeline/time_utils.py
phs/timeline/timeline.py
phs/utils/__init__.py
phs/utils/coverage.py
phs/utils/eps_utils.py
phs/utils/output.py
phs/utils/plots.py
phs/utils/session_file.py
phs/utils/setup.py
phs/utils/time.py
juice_phs-0.8.1.dist-info/LICENSE.md
juice_phs-0.8.1.dist-info/METADATA
juice_phs-0.8.1.dist-info/WHEEL
juice_phs-0.8.1.dist-info/entry_points.txt
juice_phs-0.8.1.dist-info/RECORD
