Metadata-Version: 2.3
Name: juice-phs
Version: 0.8.1
Summary: A Pointing Tool OSVE wrapper
License: European Space Agency Public License (ESA-PL) Permissive (Type 3) – v2.4
Author: Marc Costa
Author-email: marc.costa@ext.esa.int
Requires-Python: >=3.8,<4.0
Classifier: Development Status :: 4 - Beta
Classifier: Intended Audience :: Developers
Classifier: License :: Other/Proprietary License
Classifier: Operating System :: OS Independent
Classifier: Programming Language :: Python
Classifier: Programming Language :: Python :: 3
Classifier: Programming Language :: Python :: 3.8
Classifier: Programming Language :: Python :: 3.9
Classifier: Programming Language :: Python :: 3.10
Classifier: Programming Language :: Python :: 3.11
Classifier: Programming Language :: Python :: 3.12
Classifier: Programming Language :: Python :: 3.13
Classifier: Topic :: Software Development :: Libraries :: Python Modules
Classifier: Typing :: Typed
Requires-Dist: PyAstronomy (>=0.22.0)
Requires-Dist: jsonschema (>=4.23.0)
Requires-Dist: numpy (>=1.26.4)
Requires-Dist: planetary_coverage (>=1.1.1)
Requires-Dist: plotly (>=5.24.1)
Requires-Dist: python-dotenv (>=1.1.0)
Requires-Dist: requests (>=2.32.3)
Requires-Dist: spiceypy (>=5.1.2)
Requires-Dist: tqdm (>=4.66.5)
Project-URL: Documentation, https://juicesoc.esac.esa.int/panel/#/navigation/help
Project-URL: Homepage, https://gitlab.esa.int/juice-soc-public/python/juice-phs
Project-URL: Repository, https://gitlab.esa.int/juice-soc-public/python/juice-phs
